bitpermissions/__init__.py
bitpermissions/permissions.py
bitpermissions-0.1.0.dist-info/DESCRIPTION.rst
bitpermissions-0.1.0.dist-info/METADATA
bitpermissions-0.1.0.dist-info/RECORD
bitpermissions-0.1.0.dist-info/WHEEL
bitpermissions-0.1.0.dist-info/metadata.json
bitpermissions-0.1.0.dist-info/top_level.txt
