Metadata-Version: 2.0
Name: bitpermissions
Version: 0.1.0
Summary: Simple bit permissions
Home-page: https://github.com/Brian-Williams/bitpermissions
Author: Brian Williams
Author-email: briancmwilliams@gmail.com
License: MIT
Keywords: permissions
Platform: UNKNOWN
Classifier: Development Status :: 3 - Alpha
Classifier: Intended Audience :: Developers
Classifier: License :: OSI Approved :: MIT License
Classifier: Programming Language :: Python :: 2
Classifier: Programming Language :: Python :: 2.7
Classifier: Programming Language :: Python :: 3
Classifier: Programming Language :: Python :: 3.3
Classifier: Programming Language :: Python :: 3.4
Classifier: Programming Language :: Python :: 3.5
Classifier: Programming Language :: Python :: 3.6
Provides-Extra: test
Requires-Dist: flake8; extra == 'test'
Requires-Dist: pytest; extra == 'test'
